{
  "version": "7",
  "dialect": "postgresql",
  "entries": [
    {
      "idx": 0,
      "version": "7",
      "when": 1781864917146,
      "tag": "0000_fluffy_hammerhead",
      "breakpoints": true
    },
    {
      "idx": 1,
      "version": "7",
      "when": 1781931936642,
      "tag": "0001_illegal_timeslip",
      "breakpoints": true
    },
    {
      "idx": 2,
      "version": "7",
      "when": 1781937747359,
      "tag": "0002_tearful_squadron_sinister",
      "breakpoints": true
    },
    {
      "idx": 3,
      "version": "7",
      "when": 1781941939922,
      "tag": "0003_harsh_moondragon",
      "breakpoints": true
    },
    {
      "idx": 4,
      "version": "7",
      "when": 1782115869389,
      "tag": "0004_acoustic_klaw",
      "breakpoints": true
    },
    {
      "idx": 5,
      "version": "7",
      "when": 1782199652563,
      "tag": "0005_slim_pet_avengers",
      "breakpoints": true
    },
    {
      "idx": 6,
      "version": "7",
      "when": 1782274450899,
      "tag": "0006_tricky_vermin",
      "breakpoints": true
    },
    {
      "idx": 7,
      "version": "7",
      "when": 1782278817378,
      "tag": "0007_wide_beast",
      "breakpoints": true
    },
    {
      "idx": 8,
      "version": "7",
      "when": 1782314364306,
      "tag": "0008_funny_silverclaw",
      "breakpoints": true
    },
    {
      "idx": 9,
      "version": "7",
      "when": 1782366493298,
      "tag": "0009_black_iron_patriot",
      "breakpoints": true
    },
    {
      "idx": 10,
      "version": "7",
      "when": 1782380305931,
      "tag": "0010_audit_immutable",
      "breakpoints": true
    },
    {
      "idx": 11,
      "version": "7",
      "when": 1782500110433,
      "tag": "0011_minor_hydra",
      "breakpoints": true
    },
    {
      "idx": 12,
      "version": "7",
      "when": 1782537473876,
      "tag": "0012_stale_iceman",
      "breakpoints": true
    },
    {
      "idx": 13,
      "version": "7",
      "when": 1782545171287,
      "tag": "0013_messy_gressill",
      "breakpoints": true
    },
    {
      "idx": 14,
      "version": "7",
      "when": 1782737204876,
      "tag": "0014_right_warbound",
      "breakpoints": true
    }
  ]
}